samples/__init__.py
samples/custom/__init__.py
samples/custom/custom_backend.py
samples/custom/custom_exporter.py
slo_generator/__init__.py
slo_generator/cli.py
slo_generator/compute.py
slo_generator/constants.py
slo_generator/report.py
slo_generator/utils.py
slo_generator/api/__init__.py
slo_generator/api/main.py
slo_generator/backends/__init__.py
slo_generator/backends/cloud_monitoring.py
slo_generator/backends/cloud_monitoring_mql.py
slo_generator/backends/cloud_service_monitoring.py
slo_generator/backends/datadog.py
slo_generator/backends/dynatrace.py
slo_generator/backends/elasticsearch.py
slo_generator/backends/open_search.py
slo_generator/backends/prometheus.py
slo_generator/backends/splunk.py
slo_generator/exporters/__init__.py
slo_generator/exporters/base.py
slo_generator/exporters/bigquery.py
slo_generator/exporters/cloud_monitoring.py
slo_generator/exporters/cloudevent.py
slo_generator/exporters/datadog.py
slo_generator/exporters/dynatrace.py
slo_generator/exporters/prometheus.py
slo_generator/exporters/prometheus_self.py
slo_generator/exporters/pubsub.py
slo_generator/migrations/__init__.py
slo_generator/migrations/migrator.py
tests/unit/__init__.py
tests/unit/test_cli.py
tests/unit/test_compute.py
tests/unit/test_migrate.py
tests/unit/test_report.py
tests/unit/test_stubs.py
tests/unit/test_utils.py
tests/unit/backends/__init__.py
tests/unit/backends/test_cloud_monitoring_mql.py
tests/unit/backends/test_elasticsearch.py
tests/unit/backends/test_opensearch.py
tests/unit/backends/test_splunk.py
slo_generator-2.6.0.dist-info/LICENSE
slo_generator-2.6.0.dist-info/METADATA
slo_generator-2.6.0.dist-info/WHEEL
slo_generator-2.6.0.dist-info/entry_points.txt
slo_generator-2.6.0.dist-info/top_level.txt
slo_generator-2.6.0.dist-info/RECORD
