Metadata-Version: 2.1
Name: slo-generator
Version: 2.6.0
Summary: SLO Generator
Home-page: https://github.com/google/slo-generator
Author: Google Inc.
Author-email: olivier.cervello@gmail.com
Maintainer: Laurent VAYLET
Maintainer-email: laurent.vaylet@gmail.com
License: Apache License 2.0
Keywords: slo,sli,generator,gcp
Classifier: Development Status :: 5 - Production/Stable
Classifier: Environment :: Console
Classifier: Intended Audience :: Developers
Classifier: Intended Audience :: System Administrators
Classifier: License :: OSI Approved :: Apache Software License
Classifier: Programming Language :: Python
Classifier: Programming Language :: Python :: 3.7
Classifier: Programming Language :: Python :: 3.8
Classifier: Programming Language :: Python :: 3.9
Classifier: Programming Language :: Python :: 3.10
Classifier: Topic :: Software Development :: Build Tools
Classifier: Topic :: System :: Monitoring
Requires-Python: <4,>=3.7
License-File: LICENSE
Requires-Dist: pyyaml
Requires-Dist: ruamel.yaml
Requires-Dist: python-dateutil
Requires-Dist: click
Requires-Dist: setuptools >=65.5.1
Requires-Dist: certifi >=2023.07.22
Provides-Extra: api
Requires-Dist: Flask ; extra == 'api'
Requires-Dist: gunicorn ; extra == 'api'
Requires-Dist: cloudevents ; extra == 'api'
Requires-Dist: functions-framework ; extra == 'api'
Requires-Dist: requests ; extra == 'api'
Provides-Extra: bigquery
Requires-Dist: google-api-python-client ; extra == 'bigquery'
Requires-Dist: google-cloud-bigquery ; extra == 'bigquery'
Provides-Extra: cloud_monitoring
Requires-Dist: google-api-python-client ; extra == 'cloud_monitoring'
Requires-Dist: google-cloud-monitoring ; extra == 'cloud_monitoring'
Provides-Extra: cloud_service_monitoring
Requires-Dist: google-api-python-client ; extra == 'cloud_service_monitoring'
Requires-Dist: google-cloud-monitoring ; extra == 'cloud_service_monitoring'
Provides-Extra: cloud_storage
Requires-Dist: google-api-python-client ; extra == 'cloud_storage'
Requires-Dist: google-cloud-storage ; extra == 'cloud_storage'
Provides-Extra: cloudevent
Requires-Dist: cloudevents ; extra == 'cloudevent'
Provides-Extra: datadog
Requires-Dist: datadog ; extra == 'datadog'
Requires-Dist: retrying ==1.3.4 ; extra == 'datadog'
Provides-Extra: dev
Requires-Dist: pip >=23.3 ; extra == 'dev'
Requires-Dist: wheel ; extra == 'dev'
Requires-Dist: flake8 ; extra == 'dev'
Requires-Dist: black ; extra == 'dev'
Requires-Dist: isort ; extra == 'dev'
Requires-Dist: mock ; extra == 'dev'
Requires-Dist: pytest ; extra == 'dev'
Requires-Dist: pytest-cov ; extra == 'dev'
Requires-Dist: pylint ; extra == 'dev'
Requires-Dist: pytype ; extra == 'dev'
Requires-Dist: mypy ; extra == 'dev'
Requires-Dist: types-PyYAML ; extra == 'dev'
Requires-Dist: types-python-dateutil ; extra == 'dev'
Requires-Dist: types-setuptools ; extra == 'dev'
Requires-Dist: types-requests ; extra == 'dev'
Requires-Dist: types-protobuf ; extra == 'dev'
Requires-Dist: pre-commit ; extra == 'dev'
Requires-Dist: bandit ; extra == 'dev'
Requires-Dist: GitPython >=3.1.35 ; extra == 'dev'
Requires-Dist: safety ==2.3.5 ; extra == 'dev'
Provides-Extra: dynatrace
Requires-Dist: requests ; extra == 'dynatrace'
Provides-Extra: elasticsearch
Requires-Dist: elasticsearch ; extra == 'elasticsearch'
Provides-Extra: opensearch
Requires-Dist: opensearch-py ; extra == 'opensearch'
Provides-Extra: prometheus
Requires-Dist: prometheus-client ; extra == 'prometheus'
Requires-Dist: prometheus-http-client ; extra == 'prometheus'
Provides-Extra: pubsub
Requires-Dist: google-api-python-client ; extra == 'pubsub'
Requires-Dist: google-cloud-pubsub ; extra == 'pubsub'
Provides-Extra: splunk
Requires-Dist: splunk-sdk ; extra == 'splunk'
